cfbench/__init__.py
cfbench/benchmark_template_row_instance.py
cfbench/cfbench.py
cfbench/cfg/OHConverter.py
cfbench/cfg/__init__.py
cfbench/cfg/analysis.py
cfbench/cfg/common.py
cfbench/dataset_data/__init__.py
cfbench/dataset_data/generate_experiment_data.py
cfbench/dataset_data/constants/__init__.py
cfbench/dataset_data/constants/var_types.py
cfbench-0.0.9.dist-info/LICENSE.txt
cfbench-0.0.9.dist-info/METADATA
cfbench-0.0.9.dist-info/WHEEL
cfbench-0.0.9.dist-info/top_level.txt
cfbench-0.0.9.dist-info/RECORD
