Metadata-Version: 2.1
Name: cfbench
Version: 0.0.9
Summary: Benchmarking tool for Counterfactual Explanations
Home-page: https://github.com/ADMAntwerp/CounterfactualBenchmark
Download-URL: https://pypi.org/project/cfbench/
Author: Raphael Mazzine Barbosa de Oliveira
License: MIT
Keywords: Counterfactual Explanations,Benchmarking,Machine Learning
License-File: LICENSE.txt
Requires-Dist: pandas
Requires-Dist: tensorflow
Requires-Dist: requests
Requires-Dist: scipy
